clickext/__init__.py
clickext/core.py
clickext/decorators.py
clickext/exceptions.py
clickext/log.py
clickext/py.typed
clickext-1.0.5.dist-info/LICENSE
clickext-1.0.5.dist-info/METADATA
clickext-1.0.5.dist-info/WHEEL
clickext-1.0.5.dist-info/RECORD
