Metadata-Version: 2.1
Name: clickext
Version: 1.0.5
Summary: Extended features for the Python click library
Home-page: https://github.com/lojoja/clickext
License: MIT
Author: lojoja
Author-email: dev@lojoja.com
Requires-Python: >=3.10.0,<4.0.0
Classifier: Development Status :: 5 - Production/Stable
Classifier: Intended Audience :: Developers
Classifier: License :: OSI Approved :: MIT License
Classifier: Operating System :: OS Independent
Classifier: Programming Language :: Python :: 3
Classifier: Programming Language :: Python :: 3.10
Classifier: Programming Language :: Python :: 3.11
Classifier: Programming Language :: Python :: 3.12
Classifier: Programming Language :: Python :: 3.13
Requires-Dist: click (>=8.0.0,<9.0.0)
Requires-Dist: pyyaml (>=6.0.0,<7.0.0)
Requires-Dist: tomli (>=2.0.1,<3.0.0)
Project-URL: Bug Tracker, https://github.com/lojoja/clickext/issues
Project-URL: Repository, https://github.com/lojoja/clickext
